{
  "title": "Conçu pour l'excellence en torréfaction",
  "subTitle": "Machinerie de précision adaptée à vos besoins de production et de conception",
  "badge": "",
  "thirdOption": "Vous cherchez une machine plus petite ?",
  "btnText": "Torréfacteurs d'échantillonnage",

  "starterKit": {
    "name": "Torréfacteurs industriels",
    "description": "Pour la production de masse dans les torréfacteurs à grande échelle",
    "price": "",
    "cents": "",
    "billingFrequency": "",
    "features": [
      "Compatibilité Cropster & Artisan",
      "Isolation thermique améliorée",
      "Tambour double paroi avec capacité étendue",
      "Contrôle de précision avec systèmes avancés",
      "Design sur mesure pour vos besoins",
      "Support dédié 24/7"
    ],
    "purchaseBtnTitle": "Découvrez nos machines",
    "purchaseLink": "/fr/products" 
  },

  "professionalToolbox": {
    "name": "Torréfacteurs boutique",
    "description": "Solution idéale pour les torréfacteurs petites et moyennes tailles",
    "price": "",
    "cents": "",
    "billingFrequency": "",
    "features": [
      "Compatibilité Cropster & Artisan",
      "Tambour double paroi avec capacité étendue",
      "Système de brûleur prémélange modulé",
      "Contrôles de vitesse du tambour et débit d'air",
      "Plaque avant en fonte",
      "Isolation thermique améliorée",
      "Maintenance et installation faciles"
    ],
    "purchaseBtnTitle": "Découvrez nos machines",
    "purchaseLink": "/fr/products" 
  }
}
